{"folder": "/Users/PeregrinePickle/Documents/School/New York University/Seminars/Melville/Presentation/text/split/bysection_bysentence/", "pos": {"ADV": 0, "NOUN": 6, "ADP": 7, "SPACE": 4, "PROPN": 0, "DET": 6, "SYM": 0, "INTJ": 0, "PART": 0, "PUNCT": 4, "VERB": 7, "X": 0, "NUM": 0, "CONJ": 1, "PRON": 1, "ADJ": 9}, "full_text": "He was seated on an old-fashioned oaken chair, wriggling all\nover with curious carving; and the bottom of which was formed of a\nstout interlacing of the same elastic stuff of which the wigwam was\nconstructed.\n\n", "filename": "md_mobydick_19_chapter16_34.txt"}