{"folder": "/Users/PeregrinePickle/Documents/School/New York University/Seminars/Melville/Presentation/text/split/bysection_bysentence/", "pos": {"ADV": 7, "NOUN": 7, "ADP": 3, "SPACE": 4, "PROPN": 2, "DET": 4, "SYM": 0, "INTJ": 0, "PART": 2, "PUNCT": 6, "VERB": 5, "X": 0, "NUM": 1, "CONJ": 0, "PRON": 0, "ADJ": 2}, "full_text": "While the Frenchman's boats,\nthen, were engaged in towing the ship one way, Stubb benevolently towed\naway at his whale the other way, ostentatiously slacking out a most\nunusually long tow-line.\n\n", "filename": "md_mobydick_94_chapter91_105.txt"}