{"folder": "/Users/PeregrinePickle/Documents/School/New York University/Seminars/Melville/Presentation/text/split/bysection_bysentence/", "pos": {"ADV": 4, "NOUN": 1, "ADP": 1, "SPACE": 3, "PROPN": 3, "DET": 3, "SYM": 0, "INTJ": 0, "PART": 0, "PUNCT": 3, "VERB": 4, "X": 0, "NUM": 0, "CONJ": 1, "PRON": 1, "ADJ": 4}, "full_text": "well\ncalled the \"Syren\"--made a noble experimental cruise; and it was thus\nthat the great Japanese Whaling Ground first became generally known.\n", "filename": "md_mobydick_104_chapter101_11.txt"}