{"folder": "/Users/PeregrinePickle/Documents/School/New York University/Seminars/Melville/Presentation/text/split/bysection_bysentence/", "pos": {"ADV": 1, "NOUN": 9, "ADP": 6, "SPACE": 2, "PROPN": 0, "DET": 6, "SYM": 0, "INTJ": 0, "PART": 0, "PUNCT": 5, "VERB": 6, "X": 0, "NUM": 0, "CONJ": 1, "PRON": 2, "ADJ": 3}, "full_text": "And in return for that courtesy, the outward-bound ship would\nreceive the latest whaling intelligence from the cruising-ground to\nwhich she may be destined, a thing of the utmost importance to her.", "filename": "md_mobydick_56_chapter53_8.txt"}