{"folder": "/Users/PeregrinePickle/Documents/School/New York University/Seminars/Melville/Presentation/text/split/bysection_bysentence/", "pos": {"ADV": 3, "NOUN": 10, "ADP": 5, "SPACE": 2, "PROPN": 0, "DET": 6, "SYM": 0, "INTJ": 0, "PART": 1, "PUNCT": 4, "VERB": 5, "X": 0, "NUM": 0, "CONJ": 1, "PRON": 0, "ADJ": 2}, "full_text": "What's the mighty difference between holding a mast's\nlightning-rod in the storm, and standing close by a mast that hasn't\ngot any lightning-rod at all in a storm?", "filename": "md_mobydick_124_chapter121_17.txt"}