{"folder": "/Users/PeregrinePickle/Documents/School/New York University/Seminars/Melville/Presentation/text/split/bysection_bysentence/", "pos": {"ADV": 3, "NOUN": 5, "ADP": 5, "SPACE": 3, "PROPN": 2, "DET": 4, "SYM": 0, "INTJ": 0, "PART": 0, "PUNCT": 4, "VERB": 4, "X": 0, "NUM": 0, "CONJ": 1, "PRON": 0, "ADJ": 2}, "full_text": "So, in a gale, the but half baffled Channel\nbillows only recoil from the base of the Eddystone, triumphantly to\noverleap its summit with their scud.\n\n\n", "filename": "md_mobydick_136_chapter133_88.txt"}