{"folder": "/Users/PeregrinePickle/Documents/School/New York University/Seminars/Melville/Presentation/text/split/bysection_bysentence/", "pos": {"ADV": 5, "NOUN": 11, "ADP": 8, "SPACE": 4, "PROPN": 3, "DET": 5, "SYM": 0, "INTJ": 0, "PART": 0, "PUNCT": 10, "VERB": 11, "X": 0, "NUM": 1, "CONJ": 2, "PRON": 2, "ADJ": 2}, "full_text": "Hence it is, that, while other ships may\nhave gone to China from New York, and back again, touching at a score\nof ports, the whale-ship, in all that interval, may not have sighted\none grain of soil; her crew having seen no man but floating seamen like\nthemselves.", "filename": "md_mobydick_90_chapter87_26.txt"}