{"folder": "/Users/PeregrinePickle/Documents/School/New York University/Seminars/Melville/Presentation/text/split/bysection_bysentence/", "pos": {"ADV": 4, "NOUN": 13, "ADP": 9, "SPACE": 4, "PROPN": 2, "DET": 4, "SYM": 0, "INTJ": 0, "PART": 0, "PUNCT": 9, "VERB": 5, "X": 0, "NUM": 0, "CONJ": 2, "PRON": 1, "ADJ": 8}, "full_text": "Soon they through dim, bewildering\nmediums saw her sidelong fading phantom, as in the gaseous Fata Morgana;\nonly the uppermost masts out of water; while fixed by infatuation, or\nfidelity, or fate, to their once lofty perches, the pagan harpooneers\nstill maintained their sinking lookouts on the sea.", "filename": "md_mobydick_138_chapter135_264.txt"}