{"folder": "/Users/PeregrinePickle/Documents/School/New York University/Seminars/Melville/Presentation/text/split/bysection_bysentence/", "pos": {"ADV": 2, "NOUN": 6, "ADP": 5, "SPACE": 2, "PROPN": 0, "DET": 2, "SYM": 0, "INTJ": 0, "PART": 0, "PUNCT": 4, "VERB": 7, "X": 0, "NUM": 0, "CONJ": 2, "PRON": 5, "ADJ": 2}, "full_text": "In life but few of them would have helped the whale, I ween, if\nperadventure he had needed it; but upon the banquet of his funeral they\nmost piously do pounce.", "filename": "md_mobydick_72_chapter69_12.txt"}