{"folder": "/Users/PeregrinePickle/Documents/School/New York University/Seminars/Melville/Presentation/text/split/bysection_bysentence/", "pos": {"ADV": 2, "NOUN": 14, "ADP": 11, "SPACE": 5, "PROPN": 0, "DET": 7, "SYM": 0, "INTJ": 0, "PART": 0, "PUNCT": 7, "VERB": 9, "X": 0, "NUM": 0, "CONJ": 2, "PRON": 2, "ADJ": 12}, "full_text": "Drawing\nacross her bow, he perceived that in accordance with the fanciful French\ntaste, the upper part of her stem-piece was carved in the likeness of a\nhuge drooping stalk, was painted green, and for thorns had copper\nspikes projecting from it here and there; the whole terminating in a\nsymmetrical folded bulb of a bright red colour.", "filename": "md_mobydick_94_chapter91_27.txt"}