{"folder": "/Users/PeregrinePickle/Documents/School/New York University/Seminars/Melville/Presentation/text/split/bysection_bysentence/", "pos": {"ADV": 5, "NOUN": 10, "ADP": 14, "SPACE": 6, "PROPN": 0, "DET": 5, "SYM": 0, "INTJ": 0, "PART": 1, "PUNCT": 10, "VERB": 9, "X": 0, "NUM": 1, "CONJ": 1, "PRON": 6, "ADJ": 13}, "full_text": "For nothing was\nthis man more remarkable, than for a certain impersonal stolidity as\nit were; impersonal, I say; for it so shaded off into the surrounding\ninfinite of things, that it seemed one with the general stolidity\ndiscernible in the whole visible world; which while pauselessly active\nin uncounted modes, still eternally holds its peace, and ignores you,\nthough you dig foundations for cathedrals.", "filename": "md_mobydick_110_chapter107_19.txt"}