{"folder": "/Users/PeregrinePickle/Documents/School/New York University/Seminars/Melville/Presentation/text/split/bysection_bysentence/", "pos": {"ADV": 5, "NOUN": 7, "ADP": 5, "SPACE": 3, "PROPN": 0, "DET": 3, "SYM": 0, "INTJ": 0, "PART": 0, "PUNCT": 5, "VERB": 6, "X": 0, "NUM": 0, "CONJ": 1, "PRON": 1, "ADJ": 2}, "full_text": "And for years\nafterwards, perhaps, ships shun the place; leaping over it as silly\nsheep leap over a vacuum, because their leader originally leaped there\nwhen a stick was held.", "filename": "md_mobydick_72_chapter69_17.txt"}