{"folder": "/Users/PeregrinePickle/Documents/School/New York University/Seminars/Melville/Presentation/text/split/bysection_bysentence/", "pos": {"ADV": 5, "NOUN": 13, "ADP": 10, "SPACE": 5, "PROPN": 0, "DET": 8, "SYM": 0, "INTJ": 0, "PART": 3, "PUNCT": 6, "VERB": 14, "X": 0, "NUM": 0, "CONJ": 3, "PRON": 1, "ADJ": 5}, "full_text": "In vain handspikes and crows were brought to bear upon the immovable\nfluke-chains, to pry them adrift from the timberheads; and so low\nhad the whale now settled that the submerged ends could not be at all\napproached, while every moment whole tons of ponderosity seemed added to\nthe sinking bulk, and the ship seemed on the point of going over.\n\n", "filename": "md_mobydick_84_chapter81_162.txt"}