{"folder": "/Users/PeregrinePickle/Documents/School/New York University/Seminars/Melville/Presentation/text/split/bysection_bysentence/", "pos": {"ADV": 2, "NOUN": 7, "ADP": 6, "SPACE": 2, "PROPN": 2, "DET": 8, "SYM": 0, "INTJ": 0, "PART": 0, "PUNCT": 3, "VERB": 4, "X": 0, "NUM": 0, "CONJ": 1, "PRON": 1, "ADJ": 5}, "full_text": "This reminds us that the Right Whale really has a sort of whisker, or\nrather a moustache, consisting of a few scattered white hairs on the\nupper part of the outer end of the lower jaw.", "filename": "md_mobydick_78_chapter75_27.txt"}