{"folder": "/Users/PeregrinePickle/Documents/School/New York University/Seminars/Melville/Presentation/text/split/bysection_bysentence/", "pos": {"ADV": 2, "NOUN": 15, "ADP": 11, "SPACE": 6, "PROPN": 2, "DET": 6, "SYM": 0, "INTJ": 0, "PART": 1, "PUNCT": 10, "VERB": 9, "X": 1, "NUM": 0, "CONJ": 2, "PRON": 5, "ADJ": 11}, "full_text": "I tell you it will\nbe more tolerable for the Fejee that salted down a lean missionary in\nhis cellar against a coming famine; it will be more tolerable for that\nprovident Fejee, I say, in the day of judgment, than for thee, civilized\nand enlightened gourmand, who nailest geese to the ground and feastest\non their bloated livers in thy pate-de-foie-gras.\n\n", "filename": "md_mobydick_68_chapter65_31.txt"}