{"folder": "/Users/PeregrinePickle/Documents/School/New York University/Seminars/Melville/Presentation/text/split/bysection_bysentence/", "pos": {"ADV": 1, "NOUN": 17, "ADP": 12, "SPACE": 3, "PROPN": 0, "DET": 9, "SYM": 0, "INTJ": 0, "PART": 3, "PUNCT": 4, "VERB": 3, "X": 0, "NUM": 1, "CONJ": 0, "PRON": 2, "ADJ": 5}, "full_text": "At one time she would come on board with a jar\nof pickles for the steward's pantry; another time with a bunch of quills\nfor the chief mate's desk, where he kept his log; a third time with a\nroll of flannel for the small of some one's rheumatic back.", "filename": "md_mobydick_23_chapter20_16.txt"}