{"folder": "/Users/PeregrinePickle/Documents/School/New York University/Seminars/Melville/Presentation/text/split/bysection_bysentence/", "pos": {"ADV": 6, "NOUN": 5, "ADP": 1, "SPACE": 3, "PROPN": 1, "DET": 3, "SYM": 0, "INTJ": 0, "PART": 1, "PUNCT": 19, "VERB": 11, "X": 0, "NUM": 0, "CONJ": 1, "PRON": 6, "ADJ": 2}, "full_text": "But I had only just lifted my foot for it,\nwhen he roared out, 'Stop that kicking!' 'Halloa,' says I, 'what's\nthe matter now, old fellow?' 'Look ye here,' says he; 'let's argue\nthe insult.", "filename": "md_mobydick_34_chapter31_32.txt"}