{"folder": "/Users/PeregrinePickle/Documents/School/New York University/Seminars/Melville/Presentation/text/split/bysection_bysentence/", "pos": {"ADV": 4, "NOUN": 8, "ADP": 1, "SPACE": 2, "PROPN": 0, "DET": 1, "SYM": 0, "INTJ": 0, "PART": 3, "PUNCT": 3, "VERB": 6, "X": 0, "NUM": 0, "CONJ": 1, "PRON": 1, "ADJ": 3}, "full_text": "Thou hast\nbeen where bell or diver never went; hast slept by many a sailor's side,\nwhere sleepless mothers would give their lives to lay them down.", "filename": "md_mobydick_73_chapter70_22.txt"}