{"folder": "/Users/PeregrinePickle/Documents/School/New York University/Seminars/Melville/Presentation/text/split/bysection_bysentence/", "pos": {"ADV": 3, "NOUN": 9, "ADP": 3, "SPACE": 3, "PROPN": 1, "DET": 3, "SYM": 0, "INTJ": 1, "PART": 1, "PUNCT": 6, "VERB": 6, "X": 0, "NUM": 0, "CONJ": 2, "PRON": 2, "ADJ": 8}, "full_text": "Curse thee, thou vain toy; and cursed\nbe all the things that cast man's eyes aloft to that heaven, whose live\nvividness but scorches him, as these old eyes are even now scorched\nwith thy light, O sun!", "filename": "md_mobydick_121_chapter118_23.txt"}