{"folder": "/Users/PeregrinePickle/Documents/School/New York University/Seminars/Melville/Presentation/text/split/bysection_bysentence/", "pos": {"ADV": 7, "NOUN": 6, "ADP": 8, "SPACE": 3, "PROPN": 0, "DET": 4, "SYM": 0, "INTJ": 0, "PART": 1, "PUNCT": 4, "VERB": 4, "X": 0, "NUM": 0, "CONJ": 1, "PRON": 2, "ADJ": 5}, "full_text": "At last he paused before it; and as in an already over-clouded sky fresh\ntroops of clouds will sometimes sail across, so over the old man's face\nthere now stole some such added gloom as this.\n\n", "filename": "md_mobydick_136_chapter133_130.txt"}