{"folder": "/Users/PeregrinePickle/Documents/School/New York University/Seminars/Melville/Presentation/text/split/bysection_bysentence/", "pos": {"ADV": 2, "NOUN": 7, "ADP": 6, "SPACE": 3, "PROPN": 4, "DET": 4, "SYM": 0, "INTJ": 0, "PART": 1, "PUNCT": 7, "VERB": 8, "X": 0, "NUM": 0, "CONJ": 2, "PRON": 1, "ADJ": 4}, "full_text": "\"Give way!\" cried Ahab to the oarsmen, and the boats darted forward to\nthe attack; but maddened by yesterday's fresh irons that corroded in\nhim, Moby Dick seemed combinedly possessed by all the angels that fell\nfrom heaven.", "filename": "md_mobydick_138_chapter135_139.txt"}