{"folder": "/Users/PeregrinePickle/Documents/School/New York University/Seminars/Melville/Presentation/text/split/bysection_bysentence/", "pos": {"ADV": 1, "NOUN": 9, "ADP": 7, "SPACE": 3, "PROPN": 1, "DET": 5, "SYM": 0, "INTJ": 0, "PART": 0, "PUNCT": 4, "VERB": 5, "X": 0, "NUM": 1, "CONJ": 3, "PRON": 0, "ADJ": 4}, "full_text": "For as this appalling ocean\nsurrounds the verdant land, so in the soul of man there lies one insular\nTahiti, full of peace and joy, but encompassed by all the horrors of the\nhalf known life.", "filename": "md_mobydick_61_chapter58_28.txt"}