{"folder": "/Users/PeregrinePickle/Documents/School/New York University/Seminars/Melville/Presentation/text/split/bysection_bysentence/", "pos": {"ADV": 0, "NOUN": 5, "ADP": 5, "SPACE": 3, "PROPN": 1, "DET": 4, "SYM": 0, "INTJ": 0, "PART": 0, "PUNCT": 3, "VERB": 1, "X": 0, "NUM": 0, "CONJ": 0, "PRON": 1, "ADJ": 6}, "full_text": "Think of\nit; sleeping all night in the same room with a wide awake pagan on his\nhams in this dreary, unaccountable Ramadan!\n\n", "filename": "md_mobydick_20_chapter17_85.txt"}