{"folder": "/Users/PeregrinePickle/Documents/School/New York University/Seminars/Melville/Presentation/text/split/bysection_bysentence/", "pos": {"ADV": 1, "NOUN": 10, "ADP": 5, "SPACE": 3, "PROPN": 1, "DET": 5, "SYM": 0, "INTJ": 0, "PART": 2, "PUNCT": 7, "VERB": 8, "X": 0, "NUM": 0, "CONJ": 0, "PRON": 2, "ADJ": 1}, "full_text": "While he was speaking these words, the howling of the shrieking,\nslanting storm without seemed to add new power to the preacher, who,\nwhen describing Jonah's sea-storm, seemed tossed by a storm himself.\n", "filename": "md_mobydick_12_chapter9_130.txt"}