{"folder": "/Users/PeregrinePickle/Documents/School/New York University/Seminars/Melville/Presentation/text/split/bysection_bysentence/", "pos": {"ADV": 4, "NOUN": 9, "ADP": 11, "SPACE": 5, "PROPN": 0, "DET": 7, "SYM": 0, "INTJ": 0, "PART": 4, "PUNCT": 10, "VERB": 12, "X": 0, "NUM": 2, "CONJ": 1, "PRON": 1, "ADJ": 11}, "full_text": "Upon hearing the frantic project of their leader, each in his own\nseparate soul had suddenly lighted, it would seem, upon the same piece\nof treachery, namely: to be foremost in breaking out, in order to be\nthe first of the three, though the last of the ten, to surrender; and\nthereby secure whatever small chance of pardon such conduct might merit.\n", "filename": "md_mobydick_57_chapter54_178.txt"}