{"folder": "/Users/PeregrinePickle/Documents/School/New York University/Seminars/Melville/Presentation/text/split/bysection_bysentence/", "pos": {"ADV": 8, "NOUN": 16, "ADP": 13, "SPACE": 7, "PROPN": 0, "DET": 11, "SYM": 0, "INTJ": 0, "PART": 0, "PUNCT": 9, "VERB": 10, "X": 0, "NUM": 0, "CONJ": 1, "PRON": 3, "ADJ": 11}, "full_text": "When he halted before the\nbinnacle, with his glance fastened on the pointed needle in the compass,\nthat glance shot like a javelin with the pointed intensity of his\npurpose; and when resuming his walk he again paused before the mainmast,\nthen, as the same riveted glance fastened upon the riveted gold coin\nthere, he still wore the same aspect of nailed firmness, only dashed\nwith a certain wild longing, if not hopefulness.\n\n", "filename": "md_mobydick_102_chapter99_2.txt"}