{"folder": "/Users/PeregrinePickle/Documents/School/New York University/Seminars/Melville/Presentation/text/split/bysection_bysentence/", "pos": {"ADV": 5, "NOUN": 11, "ADP": 11, "SPACE": 5, "PROPN": 3, "DET": 7, "SYM": 0, "INTJ": 0, "PART": 1, "PUNCT": 9, "VERB": 9, "X": 0, "NUM": 2, "CONJ": 1, "PRON": 5, "ADJ": 8}, "full_text": "Here was a man some twenty thousand miles from\nhome, by the way of Cape Horn, that is--which was the only way he could\nget there--thrown among people as strange to him as though he were in\nthe planet Jupiter; and yet he seemed entirely at his ease; preserving\nthe utmost serenity; content with his own companionship; always equal to\nhimself.", "filename": "md_mobydick_13_chapter10_22.txt"}