{"folder": "/Users/PeregrinePickle/Documents/School/New York University/Seminars/Melville/Presentation/text/split/bysection_bysentence/", "pos": {"ADV": 12, "NOUN": 13, "ADP": 9, "SPACE": 7, "PROPN": 2, "DET": 8, "SYM": 0, "INTJ": 0, "PART": 2, "PUNCT": 11, "VERB": 13, "X": 0, "NUM": 1, "CONJ": 4, "PRON": 2, "ADJ": 5}, "full_text": "But the Pequod was\nonly making a passage now; not regularly cruising; nearly all whaling\npreparatives needing supervision the mates were fully competent to, so\nthat there was little or nothing, out of himself, to employ or excite\nAhab, now; and thus chase away, for that one interval, the clouds that\nlayer upon layer were piled upon his brow, as ever all clouds choose the\nloftiest peaks to pile themselves upon.\n\n", "filename": "md_mobydick_31_chapter28_39.txt"}