{"folder": "/Users/PeregrinePickle/Documents/School/New York University/Seminars/Melville/Presentation/text/split/bysection_bysentence/", "pos": {"ADV": 4, "NOUN": 14, "ADP": 11, "SPACE": 5, "PROPN": 1, "DET": 9, "SYM": 0, "INTJ": 1, "PART": 0, "PUNCT": 8, "VERB": 10, "X": 0, "NUM": 0, "CONJ": 4, "PRON": 1, "ADJ": 3}, "full_text": "But the hours of darkness passed in peace;\nthe men who still remained at their duty toiling hard at the pumps,\nwhose clinking and clanking at intervals through the dreary night\ndismally resounded through the ship.\n\n\"At sunrise the Captain went forward, and knocking on the deck, summoned\nthe prisoners to work; but with a yell they refused.", "filename": "md_mobydick_57_chapter54_161.txt"}