{"folder": "/Users/PeregrinePickle/Documents/School/New York University/Seminars/Melville/Presentation/text/split/bysection_bysentence/", "pos": {"ADV": 0, "NOUN": 5, "ADP": 7, "SPACE": 2, "PROPN": 2, "DET": 3, "SYM": 0, "INTJ": 0, "PART": 0, "PUNCT": 3, "VERB": 2, "X": 0, "NUM": 0, "CONJ": 1, "PRON": 0, "ADJ": 3}, "full_text": "With back to the stranger ship, and face set like a flint to his own,\nAhab stood upright till alongside of the Pequod.\n\n\n\n", "filename": "md_mobydick_103_chapter100_120.txt"}