{"folder": "/Users/PeregrinePickle/Documents/School/New York University/Seminars/Melville/Presentation/text/split/bysection_bysentence/", "pos": {"ADV": 7, "NOUN": 7, "ADP": 6, "SPACE": 5, "PROPN": 3, "DET": 4, "SYM": 0, "INTJ": 0, "PART": 3, "PUNCT": 11, "VERB": 10, "X": 0, "NUM": 0, "CONJ": 2, "PRON": 5, "ADJ": 6}, "full_text": "The first time Stubb lowered with him, Pip evinced much nervousness;\nbut happily, for that time, escaped close contact with the whale; and\ntherefore came off not altogether discreditably; though Stubb observing\nhim, took care, afterwards, to exhort him to cherish his courageousness\nto the utmost, for he might often find it needful.\n\n", "filename": "md_mobydick_96_chapter93_18.txt"}