{"folder": "/Users/PeregrinePickle/Documents/School/New York University/Seminars/Melville/Presentation/text/split/bysection_bysentence/", "pos": {"ADV": 2, "NOUN": 14, "ADP": 9, "SPACE": 4, "PROPN": 0, "DET": 6, "SYM": 0, "INTJ": 0, "PART": 1, "PUNCT": 7, "VERB": 11, "X": 0, "NUM": 0, "CONJ": 3, "PRON": 3, "ADJ": 4}, "full_text": "And when those defendants were\nremonstrated with, their captain snapped his fingers in the plaintiffs'\nteeth, and assured them that by way of doxology to the deed he had done,\nhe would now retain their line, harpoons, and boat, which had remained\nattached to the whale at the time of the seizure.", "filename": "md_mobydick_92_chapter89_22.txt"}