{"folder": "/Users/PeregrinePickle/Documents/School/New York University/Seminars/Melville/Presentation/text/split/bysection_bysentence/", "pos": {"ADV": 3, "NOUN": 8, "ADP": 6, "SPACE": 3, "PROPN": 0, "DET": 6, "SYM": 0, "INTJ": 0, "PART": 0, "PUNCT": 3, "VERB": 3, "X": 0, "NUM": 0, "CONJ": 2, "PRON": 0, "ADJ": 3}, "full_text": "A\nsignificant illustration of the fact, again and again repeated in this\nbook, that the skeleton of the whale furnishes but little clue to the\nshape of his fully invested body.", "filename": "md_mobydick_107_chapter104_32.txt"}